pycounts_macqueen/__init__.py
pycounts_macqueen/plotting.py
pycounts_macqueen/pycounts.py
pycounts_macqueen-0.1.0.dist-info/LICENSE
pycounts_macqueen-0.1.0.dist-info/WHEEL
pycounts_macqueen-0.1.0.dist-info/METADATA
pycounts_macqueen-0.1.0.dist-info/RECORD
