Metadata-Version: 2.1
Name: pycounts-macqueen
Version: 0.1.0
Summary: Calculate word counts in a text file
License: MIT
Author: Alice MacQueen
Requires-Python: >=3.8
Classifier: License :: OSI Approved :: MIT License
Classifier: Programming Language :: Python :: 3
Classifier: Programming Language :: Python :: 3.10
Classifier: Programming Language :: Python :: 3.8
Classifier: Programming Language :: Python :: 3.9
Requires-Dist: matplotlib (>=3.7.1)
